mindsdb_sql/__about__.py
mindsdb_sql/__init__.py
mindsdb_sql/exceptions.py
mindsdb_sql/parser/__init__.py
mindsdb_sql/parser/lexer.py
mindsdb_sql/parser/logger.py
mindsdb_sql/parser/parser.py
mindsdb_sql/parser/utils.py
mindsdb_sql/parser/ast/__init__.py
mindsdb_sql/parser/ast/alter_table.py
mindsdb_sql/parser/ast/base.py
mindsdb_sql/parser/ast/commit_transaction.py
mindsdb_sql/parser/ast/create.py
mindsdb_sql/parser/ast/delete.py
mindsdb_sql/parser/ast/describe.py
mindsdb_sql/parser/ast/drop.py
mindsdb_sql/parser/ast/explain.py
mindsdb_sql/parser/ast/insert.py
mindsdb_sql/parser/ast/rollback_transaction.py
mindsdb_sql/parser/ast/set.py
mindsdb_sql/parser/ast/show.py
mindsdb_sql/parser/ast/start_transaction.py
mindsdb_sql/parser/ast/update.py
mindsdb_sql/parser/ast/use.py
mindsdb_sql/parser/ast/variable.py
mindsdb_sql/parser/ast/select/__init__.py
mindsdb_sql/parser/ast/select/case.py
mindsdb_sql/parser/ast/select/common_table_expression.py
mindsdb_sql/parser/ast/select/constant.py
mindsdb_sql/parser/ast/select/data.py
mindsdb_sql/parser/ast/select/identifier.py
mindsdb_sql/parser/ast/select/join.py
mindsdb_sql/parser/ast/select/native_query.py
mindsdb_sql/parser/ast/select/operation.py
mindsdb_sql/parser/ast/select/order_by.py
mindsdb_sql/parser/ast/select/parameter.py
mindsdb_sql/parser/ast/select/select.py
mindsdb_sql/parser/ast/select/star.py
mindsdb_sql/parser/ast/select/tuple.py
mindsdb_sql/parser/ast/select/type_cast.py
mindsdb_sql/parser/ast/select/union.py
mindsdb_sql/parser/dialects/__init__.py
mindsdb_sql/parser/dialects/mindsdb/__init__.py
mindsdb_sql/parser/dialects/mindsdb/agents.py
mindsdb_sql/parser/dialects/mindsdb/chatbot.py
mindsdb_sql/parser/dialects/mindsdb/create_database.py
mindsdb_sql/parser/dialects/mindsdb/create_job.py
mindsdb_sql/parser/dialects/mindsdb/create_ml_engine.py
mindsdb_sql/parser/dialects/mindsdb/create_predictor.py
mindsdb_sql/parser/dialects/mindsdb/create_view.py
mindsdb_sql/parser/dialects/mindsdb/drop_dataset.py
mindsdb_sql-0.21.0.dist-info/LICENSE
mindsdb_sql-0.21.0.dist-info/METADATA
mindsdb_sql-0.21.0.dist-info/WHEEL
mindsdb_sql-0.21.0.dist-info/top_level.txt
mindsdb_sql-0.21.0.dist-info/RECORD
